{"tile":"a15_q04","points":[{"i":26697,"l":"4356.e2","iso":"4356.e","N":4356,"r":1,"t":"Z/3Z","to":3,"cm":1,"az":2.7113307,"al":0.6261937,"lp":11,"ci":1,"cs":2},{"i":28519,"l":"4641.b3","iso":"4641.b","N":4641,"r":1,"t":"Z/2Z \u00d7 Z/4Z","to":8,"cm":0,"az":2.682083,"al":0.5944992,"lp":17,"ci":5,"cs":6},{"i":32238,"l":"5184.r1","iso":"5184.r","N":5184,"r":1,"t":"0","to":1,"cm":0,"az":2.783978,"al":0.5257328,"lp":3,"ci":0,"cs":4},{"i":28518,"l":"4641.b2","iso":"4641.b","N":4641,"r":1,"t":"Z/2Z \u00d7 Z/2Z","to":4,"cm":0,"az":2.6777661,"al":0.592333,"lp":17,"ci":2,"cs":6},{"i":28520,"l":"4641.b4","iso":"4641.b","N":4641,"r":1,"t":"Z/4Z","to":4,"cm":0,"az":2.6781504,"al":0.5904101,"lp":17,"ci":3,"cs":6},{"i":28521,"l":"4641.b5","iso":"4641.b","N":4641,"r":1,"t":"Z/4Z","to":4,"cm":0,"az":2.6823359,"al":0.5923142,"lp":17,"ci":4,"cs":6},{"i":32256,"l":"5184.bc1","iso":"5184.bc","N":5184,"r":1,"t":"0","to":1,"cm":0,"az":2.7886817,"al":0.5260834,"lp":3,"ci":0,"cs":2},{"i":31251,"l":"5040.g6","iso":"5040.g","N":5040,"r":1,"t":"Z/2Z \u00d7 Z/2Z","to":4,"cm":0,"az":2.772661,"al":0.5454932,"lp":7,"ci":7,"cs":8},{"i":29626,"l":"4800.bn1","iso":"4800.bn","N":4800,"r":1,"t":"Z/2Z","to":2,"cm":0,"az":2.6850547,"al":0.574454,"lp":5,"ci":0,"cs":2},{"i":29627,"l":"4800.bn2","iso":"4800.bn","N":4800,"r":1,"t":"Z/2Z","to":2,"cm":0,"az":2.6809527,"al":0.5709242,"lp":5,"ci":1,"cs":2},{"i":28517,"l":"4641.b1","iso":"4641.b","N":4641,"r":1,"t":"Z/2Z","to":2,"cm":0,"az":2.6816978,"al":0.5954094,"lp":17,"ci":0,"cs":6},{"i":28522,"l":"4641.b6","iso":"4641.b","N":4641,"r":1,"t":"Z/2Z","to":2,"cm":0,"az":2.6815607,"al":0.5961989,"lp":17,"ci":1,"cs":6},{"i":31249,"l":"5040.g4","iso":"5040.g","N":5040,"r":1,"t":"Z/2Z","to":2,"cm":0,"az":2.7696852,"al":0.543723,"lp":7,"ci":2,"cs":8},{"i":31252,"l":"5040.g7","iso":"5040.g","N":5040,"r":1,"t":"Z/2Z","to":2,"cm":0,"az":2.7672919,"al":0.5410314,"lp":7,"ci":4,"cs":8},{"i":31253,"l":"5040.g8","iso":"5040.g","N":5040,"r":1,"t":"Z/2Z","to":2,"cm":0,"az":2.7721131,"al":0.5387812,"lp":7,"ci":5,"cs":8},{"i":30106,"l":"4862.b1","iso":"4862.b","N":4862,"r":1,"t":"Z/2Z","to":2,"cm":0,"az":2.7620174,"al":0.5646616,"lp":17,"ci":0,"cs":4},{"i":30107,"l":"4862.b2","iso":"4862.b","N":4862,"r":1,"t":"Z/2Z","to":2,"cm":0,"az":2.7575593,"al":0.5664031,"lp":17,"ci":1,"cs":4},{"i":31516,"l":"5070.k2","iso":"5070.k","N":5070,"r":1,"t":"Z/2Z","to":2,"cm":0,"az":2.7487463,"al":0.5395081,"lp":13,"ci":1,"cs":4},{"i":31517,"l":"5070.k3","iso":"5070.k","N":5070,"r":1,"t":"Z/2Z","to":2,"cm":0,"az":2.7501147,"al":0.5371184,"lp":13,"ci":2,"cs":4},{"i":26526,"l":"4335.c2","iso":"4335.c","N":4335,"r":0,"t":"Z/2Z \u00d7 Z/2Z","to":4,"cm":0,"az":2.7747148,"al":0.6285653,"lp":17,"ci":5,"cs":8},{"i":26529,"l":"4335.c5","iso":"4335.c","N":4335,"r":0,"t":"Z/2Z \u00d7 Z/2Z","to":4,"cm":0,"az":2.7730302,"al":0.6311217,"lp":17,"ci":6,"cs":8},{"i":26530,"l":"4335.c6","iso":"4335.c","N":4335,"r":0,"t":"Z/2Z \u00d7 Z/2Z","to":4,"cm":0,"az":2.7730445,"al":0.6337148,"lp":17,"ci":7,"cs":8},{"i":31366,"l":"5040.bm4","iso":"5040.bm","N":5040,"r":1,"t":"Z/2Z","to":2,"cm":0,"az":2.7916494,"al":0.5403844,"lp":7,"ci":2,"cs":4},{"i":25875,"l":"4225.c2","iso":"4225.c","N":4225,"r":1,"t":"0","to":1,"cm":0,"az":2.7637922,"al":0.6431532,"lp":13,"ci":1,"cs":2},{"i":31284,"l":"5040.n1","iso":"5040.n","N":5040,"r":1,"t":"Z/2Z","to":2,"cm":0,"az":2.6289691,"al":0.5421048,"lp":7,"ci":0,"cs":2},{"i":31285,"l":"5040.n2","iso":"5040.n","N":5040,"r":1,"t":"Z/2Z","to":2,"cm":0,"az":2.6255244,"al":0.5420405,"lp":7,"ci":1,"cs":2},{"i":28351,"l":"4606.a1","iso":"4606.a","N":4606,"r":2,"t":"Z/2Z","to":2,"cm":0,"az":2.6332748,"al":0.5979645,"lp":47,"ci":0,"cs":2},{"i":28352,"l":"4606.a2","iso":"4606.a","N":4606,"r":2,"t":"Z/2Z","to":2,"cm":0,"az":2.6274657,"al":0.5951318,"lp":47,"ci":1,"cs":2},{"i":26281,"l":"4290.m1","iso":"4290.m","N":4290,"r":1,"t":"Z/2Z","to":2,"cm":0,"az":2.7645216,"al":0.6367513,"lp":13,"ci":0,"cs":2},{"i":26282,"l":"4290.m2","iso":"4290.m","N":4290,"r":1,"t":"Z/2Z","to":2,"cm":0,"az":2.7600348,"al":0.6345256,"lp":13,"ci":1,"cs":2},{"i":32250,"l":"5184.z1","iso":"5184.z","N":5184,"r":0,"t":"0","to":1,"cm":0,"az":2.7201346,"al":0.5250713,"lp":3,"ci":0,"cs":2},{"i":32251,"l":"5184.z2","iso":"5184.z","N":5184,"r":0,"t":"0","to":1,"cm":0,"az":2.7165687,"al":0.5243707,"lp":3,"ci":1,"cs":2},{"i":29131,"l":"4725.d1","iso":"4725.d","N":4725,"r":1,"t":"0","to":1,"cm":0,"az":2.6890295,"al":0.582075,"lp":7,"ci":0,"cs":1},{"i":28221,"l":"4590.a2","iso":"4590.a","N":4590,"r":1,"t":"Z/3Z","to":3,"cm":0,"az":2.6182849,"al":0.5977884,"lp":17,"ci":1,"cs":2},{"i":31003,"l":"4998.b1","iso":"4998.b","N":4998,"r":1,"t":"Z/2Z","to":2,"cm":0,"az":2.6259695,"al":0.5485076,"lp":17,"ci":0,"cs":2},{"i":31004,"l":"4998.b2","iso":"4998.b","N":4998,"r":1,"t":"Z/2Z","to":2,"cm":0,"az":2.6219139,"al":0.5455558,"lp":17,"ci":1,"cs":2},{"i":31088,"l":"5005.a1","iso":"5005.a","N":5005,"r":1,"t":"0","to":1,"cm":0,"az":2.6396414,"al":0.5449074,"lp":13,"ci":0,"cs":1},{"i":31471,"l":"5060.b1","iso":"5060.b","N":5060,"r":2,"t":"0","to":1,"cm":0,"az":2.739892,"al":0.5397057,"lp":23,"ci":0,"cs":1},{"i":26379,"l":"4305.f3","iso":"4305.f","N":4305,"r":0,"t":"Z/2Z \u00d7 Z/4Z","to":8,"cm":0,"az":2.7506017,"al":0.6345882,"lp":41,"ci":4,"cs":6},{"i":26381,"l":"4305.f5","iso":"4305.f","N":4305,"r":0,"t":"Z/8Z","to":8,"cm":0,"az":2.7497435,"al":0.6371298,"lp":41,"ci":5,"cs":6},{"i":30058,"l":"4851.c1","iso":"4851.c","N":4851,"r":0,"t":"Z/2Z","to":2,"cm":0,"az":2.6374161,"al":0.5657532,"lp":11,"ci":0,"cs":2},{"i":30059,"l":"4851.c2","iso":"4851.c","N":4851,"r":0,"t":"Z/2Z","to":2,"cm":0,"az":2.63753,"al":0.5625959,"lp":11,"ci":1,"cs":2},{"i":26220,"l":"4284.d1","iso":"4284.d","N":4284,"r":1,"t":"Z/2Z","to":2,"cm":0,"az":2.7089646,"al":0.6375452,"lp":17,"ci":0,"cs":2},{"i":26221,"l":"4284.d2","iso":"4284.d","N":4284,"r":1,"t":"Z/2Z","to":2,"cm":0,"az":2.7010617,"al":0.6347337,"lp":17,"ci":1,"cs":2},{"i":26525,"l":"4335.c1","iso":"4335.c","N":4335,"r":0,"t":"Z/2Z","to":2,"cm":0,"az":2.7737748,"al":0.6327684,"lp":17,"ci":0,"cs":8},{"i":26527,"l":"4335.c3","iso":"4335.c","N":4335,"r":0,"t":"Z/2Z","to":2,"cm":0,"az":2.7718887,"al":0.6335942,"lp":17,"ci":1,"cs":8},{"i":26528,"l":"4335.c4","iso":"4335.c","N":4335,"r":0,"t":"Z/2Z","to":2,"cm":0,"az":2.7715981,"al":0.6323968,"lp":17,"ci":2,"cs":8},{"i":26531,"l":"4335.c7","iso":"4335.c","N":4335,"r":0,"t":"Z/2Z","to":2,"cm":0,"az":2.7654923,"al":0.63224,"lp":17,"ci":3,"cs":8},{"i":26532,"l":"4335.c8","iso":"4335.c","N":4335,"r":0,"t":"Z/2Z","to":2,"cm":0,"az":2.7678604,"al":0.6292951,"lp":17,"ci":4,"cs":8},{"i":28788,"l":"4675.f1","iso":"4675.f","N":4675,"r":1,"t":"0","to":1,"cm":0,"az":2.6647432,"al":0.5873133,"lp":17,"ci":0,"cs":1},{"i":26069,"l":"4263.c2","iso":"4263.c","N":4263,"r":0,"t":"Z/4Z","to":4,"cm":0,"az":2.7625317,"al":0.638271,"lp":29,"ci":3,"cs":6},{"i":26070,"l":"4263.c3","iso":"4263.c","N":4263,"r":0,"t":"Z/2Z \u00d7 Z/2Z","to":4,"cm":0,"az":2.7666243,"al":0.6382336,"lp":29,"ci":4,"cs":6},{"i":26071,"l":"4263.c4","iso":"4263.c","N":4263,"r":0,"t":"Z/2Z \u00d7 Z/2Z","to":4,"cm":0,"az":2.7659634,"al":0.6408131,"lp":29,"ci":5,"cs":6},{"i":31590,"l":"5082.b1","iso":"5082.b","N":5082,"r":0,"t":"Z/2Z","to":2,"cm":0,"az":2.7226391,"al":0.5373958,"lp":11,"ci":0,"cs":2},{"i":31591,"l":"5082.b2","iso":"5082.b","N":5082,"r":0,"t":"Z/2Z","to":2,"cm":0,"az":2.7191319,"al":0.535579,"lp":11,"ci":1,"cs":2},{"i":27890,"l":"4550.i1","iso":"4550.i","N":4550,"r":1,"t":"0","to":1,"cm":0,"az":2.7541965,"al":0.604661,"lp":13,"ci":0,"cs":1},{"i":27451,"l":"4464.t2","iso":"4464.t","N":4464,"r":1,"t":"Z/2Z \u00d7 Z/2Z","to":4,"cm":0,"az":2.700244,"al":0.6104572,"lp":31,"ci":2,"cs":4},{"i":27453,"l":"4464.t4","iso":"4464.t","N":4464,"r":1,"t":"Z/4Z","to":4,"cm":0,"az":2.7029217,"al":0.6131565,"lp":31,"ci":3,"cs":4},{"i":29884,"l":"4830.v1","iso":"4830.v","N":4830,"r":1,"t":"Z/2Z","to":2,"cm":0,"az":2.7288451,"al":0.5685757,"lp":23,"ci":0,"cs":2},{"i":29885,"l":"4830.v2","iso":"4830.v","N":4830,"r":1,"t":"Z/2Z","to":2,"cm":0,"az":2.7253329,"al":0.5661248,"lp":23,"ci":1,"cs":2},{"i":27534,"l":"4480.k1","iso":"4480.k","N":4480,"r":0,"t":"Z/2Z","to":2,"cm":0,"az":2.7297082,"al":0.6130972,"lp":7,"ci":0,"cs":2},{"i":27535,"l":"4480.k2","iso":"4480.k","N":4480,"r":0,"t":"Z/2Z","to":2,"cm":0,"az":2.7278591,"al":0.6109782,"lp":7,"ci":1,"cs":2},{"i":29720,"l":"4805.g1","iso":"4805.g","N":4805,"r":1,"t":"0","to":1,"cm":0,"az":2.7574578,"al":0.5722204,"lp":31,"ci":0,"cs":1},{"i":25870,"l":"4225.a1","iso":"4225.a","N":4225,"r":0,"t":"0","to":1,"cm":0,"az":2.7002687,"al":0.6423077,"lp":13,"ci":0,"cs":2},{"i":25871,"l":"4225.a2","iso":"4225.a","N":4225,"r":0,"t":"0","to":1,"cm":0,"az":2.692945,"al":0.6436932,"lp":13,"ci":1,"cs":2},{"i":27609,"l":"4495.b1","iso":"4495.b","N":4495,"r":1,"t":"0","to":1,"cm":0,"az":2.6944509,"al":0.6115255,"lp":31,"ci":0,"cs":1},{"i":31076,"l":"5002.b1","iso":"5002.b","N":5002,"r":1,"t":"Z/2Z","to":2,"cm":0,"az":2.7283174,"al":0.5482435,"lp":61,"ci":0,"cs":2},{"i":31077,"l":"5002.b2","iso":"5002.b","N":5002,"r":1,"t":"Z/2Z","to":2,"cm":0,"az":2.7258851,"al":0.5463263,"lp":61,"ci":1,"cs":2},{"i":25967,"l":"4232.a1","iso":"4232.a","N":4232,"r":1,"t":"0","to":1,"cm":0,"az":2.6904712,"al":0.6414632,"lp":23,"ci":0,"cs":1},{"i":25976,"l":"4232.i1","iso":"4232.i","N":4232,"r":1,"t":"0","to":1,"cm":0,"az":2.7065847,"al":0.641305,"lp":23,"ci":0,"cs":1},{"i":30070,"l":"4851.k2","iso":"4851.k","N":4851,"r":0,"t":"0","to":1,"cm":0,"az":2.7247609,"al":0.5665959,"lp":11,"ci":1,"cs":3},{"i":26378,"l":"4305.f2","iso":"4305.f","N":4305,"r":0,"t":"Z/2Z \u00d7 Z/2Z","to":4,"cm":0,"az":2.7471591,"al":0.6310441,"lp":41,"ci":2,"cs":6},{"i":26380,"l":"4305.f4","iso":"4305.f","N":4305,"r":0,"t":"Z/4Z","to":4,"cm":0,"az":2.7485603,"al":0.6320708,"lp":41,"ci":3,"cs":6},{"i":29485,"l":"4794.b1","iso":"4794.b","N":4794,"r":1,"t":"Z/2Z","to":2,"cm":0,"az":2.7499984,"al":0.5761447,"lp":47,"ci":0,"cs":2},{"i":29486,"l":"4794.b2","iso":"4794.b","N":4794,"r":1,"t":"Z/2Z","to":2,"cm":0,"az":2.746514,"al":0.5737116,"lp":47,"ci":1,"cs":2},{"i":26464,"l":"4320.h1","iso":"4320.h","N":4320,"r":0,"t":"0","to":1,"cm":0,"az":2.7815954,"al":0.632377,"lp":5,"ci":0,"cs":1},{"i":29693,"l":"4800.cn1","iso":"4800.cn","N":4800,"r":0,"t":"0","to":1,"cm":0,"az":2.7103202,"al":0.5718817,"lp":5,"ci":0,"cs":1},{"i":26068,"l":"4263.c1","iso":"4263.c","N":4263,"r":0,"t":"Z/2Z","to":2,"cm":0,"az":2.7628104,"al":0.6414517,"lp":29,"ci":0,"cs":6},{"i":26072,"l":"4263.c5","iso":"4263.c","N":4263,"r":0,"t":"Z/2Z","to":2,"cm":0,"az":2.7628585,"al":0.6414729,"lp":29,"ci":1,"cs":6},{"i":26073,"l":"4263.c6","iso":"4263.c","N":4263,"r":0,"t":"Z/2Z","to":2,"cm":0,"az":2.7594462,"al":0.6407509,"lp":29,"ci":2,"cs":6},{"i":28173,"l":"4576.c1","iso":"4576.c","N":4576,"r":1,"t":"0","to":1,"cm":0,"az":2.7137942,"al":0.6000701,"lp":13,"ci":0,"cs":1},{"i":31217,"l":"5037.c1","iso":"5037.c","N":5037,"r":1,"t":"Z/2Z","to":2,"cm":0,"az":2.7143296,"al":0.5442805,"lp":73,"ci":0,"cs":2},{"i":31218,"l":"5037.c2","iso":"5037.c","N":5037,"r":1,"t":"Z/2Z","to":2,"cm":0,"az":2.7060942,"al":0.5421409,"lp":73,"ci":1,"cs":2},{"i":26850,"l":"4386.j2","iso":"4386.j","N":4386,"r":0,"t":"Z/2Z \u00d7 Z/2Z","to":4,"cm":0,"az":2.745426,"al":0.6227415,"lp":43,"ci":2,"cs":4},{"i":26852,"l":"4386.j4","iso":"4386.j","N":4386,"r":0,"t":"Z/4Z","to":4,"cm":0,"az":2.7452142,"al":0.6251988,"lp":43,"ci":3,"cs":4},{"i":28105,"l":"4560.ba3","iso":"4560.ba","N":4560,"r":0,"t":"Z/2Z \u00d7 Z/2Z","to":4,"cm":0,"az":2.7693442,"al":0.603539,"lp":19,"ci":3,"cs":4},{"i":32149,"l":"5175.k1","iso":"5175.k","N":5175,"r":1,"t":"0","to":1,"cm":0,"az":2.7782159,"al":0.5281424,"lp":23,"ci":0,"cs":1},{"i":30385,"l":"4905.b2","iso":"4905.b","N":4905,"r":1,"t":"Z/2Z \u00d7 Z/2Z","to":4,"cm":0,"az":2.6673119,"al":0.5594254,"lp":109,"ci":3,"cs":4},{"i":27450,"l":"4464.t1","iso":"4464.t","N":4464,"r":1,"t":"Z/2Z","to":2,"cm":0,"az":2.7009725,"al":0.6141888,"lp":31,"ci":0,"cs":4},{"i":27452,"l":"4464.t3","iso":"4464.t","N":4464,"r":1,"t":"Z/2Z","to":2,"cm":0,"az":2.6963062,"al":0.6144823,"lp":31,"ci":1,"cs":4},{"i":28903,"l":"4692.c1","iso":"4692.c","N":4692,"r":1,"t":"0","to":1,"cm":0,"az":2.6234133,"al":0.5859158,"lp":23,"ci":0,"cs":1},{"i":27769,"l":"4524.d2","iso":"4524.d","N":4524,"r":0,"t":"Z/3Z","to":3,"cm":0,"az":2.7233698,"al":0.6065181,"lp":29,"ci":1,"cs":2},{"i":26505,"l":"4329.c1","iso":"4329.c","N":4329,"r":1,"t":"0","to":1,"cm":0,"az":2.7567028,"al":0.6312082,"lp":37,"ci":0,"cs":1},{"i":28801,"l":"4675.q1","iso":"4675.q","N":4675,"r":0,"t":"0","to":1,"cm":0,"az":2.6702696,"al":0.5872245,"lp":17,"ci":0,"cs":1},{"i":28596,"l":"4650.bd2","iso":"4650.bd","N":4650,"r":1,"t":"0","to":1,"cm":0,"az":2.6400216,"al":0.5932252,"lp":31,"ci":1,"cs":2},{"i":29515,"l":"4797.c1","iso":"4797.c","N":4797,"r":1,"t":"0","to":1,"cm":0,"az":2.7645023,"al":0.5737582,"lp":41,"ci":0,"cs":1},{"i":28337,"l":"4602.f3","iso":"4602.f","N":4602,"r":0,"t":"Z/2Z \u00d7 Z/2Z","to":4,"cm":0,"az":2.7757011,"al":0.5958723,"lp":59,"ci":2,"cs":4},{"i":28338,"l":"4602.f4","iso":"4602.f","N":4602,"r":0,"t":"Z/4Z","to":4,"cm":0,"az":2.7770052,"al":0.5949607,"lp":59,"ci":3,"cs":4},{"i":29902,"l":"4830.bb1","iso":"4830.bb","N":4830,"r":0,"t":"Z/2Z","to":2,"cm":0,"az":2.6805861,"al":0.5687563,"lp":23,"ci":0,"cs":2},{"i":29903,"l":"4830.bb2","iso":"4830.bb","N":4830,"r":0,"t":"Z/2Z","to":2,"cm":0,"az":2.6762749,"al":0.5660538,"lp":23,"ci":1,"cs":2},{"i":27308,"l":"4440.f2","iso":"4440.f","N":4440,"r":0,"t":"Z/2Z \u00d7 Z/2Z","to":4,"cm":0,"az":2.6563627,"al":0.6134642,"lp":37,"ci":2,"cs":4},{"i":27309,"l":"4440.f3","iso":"4440.f","N":4440,"r":0,"t":"Z/4Z","to":4,"cm":0,"az":2.6617881,"al":0.6164123,"lp":37,"ci":3,"cs":4},{"i":31872,"l":"5133.c1","iso":"5133.c","N":5133,"r":1,"t":"0","to":1,"cm":0,"az":2.7832592,"al":0.5323313,"lp":59,"ci":0,"cs":1},{"i":28771,"l":"4674.b1","iso":"4674.b","N":4674,"r":1,"t":"0","to":1,"cm":0,"az":2.6465656,"al":0.5893185,"lp":41,"ci":0,"cs":1},{"i":26377,"l":"4305.f1","iso":"4305.f","N":4305,"r":0,"t":"Z/2Z","to":2,"cm":0,"az":2.7528841,"al":0.6342687,"lp":41,"ci":0,"cs":6},{"i":26382,"l":"4305.f6","iso":"4305.f","N":4305,"r":0,"t":"Z/2Z","to":2,"cm":0,"az":2.747856,"al":0.6356884,"lp":41,"ci":1,"cs":6},{"i":29773,"l":"4816.d2","iso":"4816.d","N":4816,"r":0,"t":"Z/4Z","to":4,"cm":0,"az":2.7508575,"al":0.5681199,"lp":43,"ci":2,"cs":4},{"i":29774,"l":"4816.d3","iso":"4816.d","N":4816,"r":0,"t":"Z/2Z \u00d7 Z/2Z","to":4,"cm":0,"az":2.7546439,"al":0.5709491,"lp":43,"ci":3,"cs":4},{"i":31747,"l":"5104.a1","iso":"5104.a","N":5104,"r":1,"t":"0","to":1,"cm":0,"az":2.6465261,"al":0.5346422,"lp":29,"ci":0,"cs":1},{"i":26849,"l":"4386.j1","iso":"4386.j","N":4386,"r":0,"t":"Z/2Z","to":2,"cm":0,"az":2.744438,"al":0.6270281,"lp":43,"ci":0,"cs":4},{"i":26851,"l":"4386.j3","iso":"4386.j","N":4386,"r":0,"t":"Z/2Z","to":2,"cm":0,"az":2.7424448,"al":0.6268665,"lp":43,"ci":1,"cs":4},{"i":28103,"l":"4560.ba1","iso":"4560.ba","N":4560,"r":0,"t":"Z/2Z","to":2,"cm":0,"az":2.7695942,"al":0.6019913,"lp":19,"ci":0,"cs":4},{"i":28104,"l":"4560.ba2","iso":"4560.ba","N":4560,"r":0,"t":"Z/2Z","to":2,"cm":0,"az":2.76967,"al":0.6035345,"lp":19,"ci":1,"cs":4},{"i":28106,"l":"4560.ba4","iso":"4560.ba","N":4560,"r":0,"t":"Z/2Z","to":2,"cm":0,"az":2.7668957,"al":0.5995384,"lp":19,"ci":2,"cs":4},{"i":27612,"l":"4495.d1","iso":"4495.d","N":4495,"r":0,"t":"0","to":1,"cm":0,"az":2.7729323,"al":0.6092976,"lp":31,"ci":0,"cs":1},{"i":28600,"l":"4650.bg1","iso":"4650.bg","N":4650,"r":0,"t":"Z/2Z","to":2,"cm":0,"az":2.6794605,"al":0.5922976,"lp":31,"ci":0,"cs":2},{"i":28601,"l":"4650.bg2","iso":"4650.bg","N":4650,"r":0,"t":"Z/2Z","to":2,"cm":0,"az":2.676469,"al":0.5899075,"lp":31,"ci":1,"cs":2},{"i":30894,"l":"4968.l1","iso":"4968.l","N":4968,"r":1,"t":"0","to":1,"cm":0,"az":2.6404368,"al":0.5497498,"lp":23,"ci":0,"cs":1},{"i":30896,"l":"4968.n1","iso":"4968.n","N":4968,"r":1,"t":"0","to":1,"cm":0,"az":2.6425245,"al":0.5496753,"lp":23,"ci":0,"cs":1},{"i":28775,"l":"4674.e1","iso":"4674.e","N":4674,"r":0,"t":"Z/2Z","to":2,"cm":0,"az":2.6746895,"al":0.5895614,"lp":41,"ci":0,"cs":2},{"i":28776,"l":"4674.e2","iso":"4674.e","N":4674,"r":0,"t":"Z/2Z","to":2,"cm":0,"az":2.6707964,"al":0.5876627,"lp":41,"ci":1,"cs":2},{"i":30384,"l":"4905.b1","iso":"4905.b","N":4905,"r":1,"t":"Z/2Z","to":2,"cm":0,"az":2.6624951,"al":0.5599509,"lp":109,"ci":0,"cs":4},{"i":30386,"l":"4905.b3","iso":"4905.b","N":4905,"r":1,"t":"Z/2Z","to":2,"cm":0,"az":2.6590742,"al":0.5608604,"lp":109,"ci":1,"cs":4},{"i":30387,"l":"4905.b4","iso":"4905.b","N":4905,"r":1,"t":"Z/2Z","to":2,"cm":0,"az":2.6591694,"al":0.5567169,"lp":109,"ci":2,"cs":4},{"i":30431,"l":"4914.j1","iso":"4914.j","N":4914,"r":0,"t":"0","to":1,"cm":0,"az":2.7096733,"al":0.5590684,"lp":13,"ci":0,"cs":1},{"i":30459,"l":"4914.bb1","iso":"4914.bb","N":4914,"r":0,"t":"0","to":1,"cm":0,"az":2.7660071,"al":0.5587275,"lp":13,"ci":0,"cs":1},{"i":25969,"l":"4232.c1","iso":"4232.c","N":4232,"r":0,"t":"0","to":1,"cm":0,"az":2.6387492,"al":0.6408222,"lp":23,"ci":0,"cs":1},{"i":27226,"l":"4425.b1","iso":"4425.b","N":4425,"r":1,"t":"0","to":1,"cm":0,"az":2.7915731,"al":0.6172703,"lp":59,"ci":0,"cs":1},{"i":27284,"l":"4437.f1","iso":"4437.f","N":4437,"r":0,"t":"0","to":1,"cm":0,"az":2.675185,"al":0.6156334,"lp":29,"ci":0,"cs":1},{"i":26113,"l":"4270.d1","iso":"4270.d","N":4270,"r":1,"t":"0","to":1,"cm":0,"az":2.7512457,"al":0.6383936,"lp":61,"ci":0,"cs":1},{"i":30935,"l":"4975.b1","iso":"4975.b","N":4975,"r":1,"t":"Z/2Z","to":2,"cm":0,"az":2.7832877,"al":0.5509476,"lp":199,"ci":0,"cs":2},{"i":30936,"l":"4975.b2","iso":"4975.b","N":4975,"r":1,"t":"Z/2Z","to":2,"cm":0,"az":2.7807327,"al":0.5485577,"lp":199,"ci":1,"cs":2},{"i":28335,"l":"4602.f1","iso":"4602.f","N":4602,"r":0,"t":"Z/2Z","to":2,"cm":0,"az":2.7772646,"al":0.5992616,"lp":59,"ci":0,"cs":4},{"i":28336,"l":"4602.f2","iso":"4602.f","N":4602,"r":0,"t":"Z/2Z","to":2,"cm":0,"az":2.7763378,"al":0.5988345,"lp":59,"ci":1,"cs":4},{"i":28305,"l":"4599.a1","iso":"4599.a","N":4599,"r":1,"t":"0","to":1,"cm":0,"az":2.7154541,"al":0.5966477,"lp":73,"ci":0,"cs":1},{"i":31724,"l":"5100.c1","iso":"5100.c","N":5100,"r":0,"t":"0","to":1,"cm":0,"az":2.7681289,"al":0.5346737,"lp":17,"ci":0,"cs":1},{"i":31729,"l":"5100.f1","iso":"5100.f","N":5100,"r":0,"t":"0","to":1,"cm":0,"az":2.7754547,"al":0.5337408,"lp":17,"ci":0,"cs":1},{"i":31735,"l":"5100.k1","iso":"5100.k","N":5100,"r":0,"t":"0","to":1,"cm":0,"az":2.6828933,"al":0.5347677,"lp":17,"ci":0,"cs":1},{"i":27307,"l":"4440.f1","iso":"4440.f","N":4440,"r":0,"t":"Z/2Z","to":2,"cm":0,"az":2.6608945,"al":0.6167029,"lp":37,"ci":0,"cs":4},{"i":27310,"l":"4440.f4","iso":"4440.f","N":4440,"r":0,"t":"Z/2Z","to":2,"cm":0,"az":2.6560204,"al":0.6174559,"lp":37,"ci":1,"cs":4},{"i":29772,"l":"4816.d1","iso":"4816.d","N":4816,"r":0,"t":"Z/2Z","to":2,"cm":0,"az":2.7583879,"al":0.5710571,"lp":43,"ci":0,"cs":4},{"i":29775,"l":"4816.d4","iso":"4816.d","N":4816,"r":0,"t":"Z/2Z","to":2,"cm":0,"az":2.7547246,"al":0.5723529,"lp":43,"ci":1,"cs":4},{"i":31434,"l":"5056.c1","iso":"5056.c","N":5056,"r":1,"t":"Z/2Z","to":2,"cm":0,"az":2.7495613,"al":0.5396839,"lp":79,"ci":0,"cs":2},{"i":31435,"l":"5056.c2","iso":"5056.c","N":5056,"r":1,"t":"Z/2Z","to":2,"cm":0,"az":2.7434762,"al":0.5377916,"lp":79,"ci":1,"cs":2},{"i":31123,"l":"5010.h2","iso":"5010.h","N":5010,"r":0,"t":"Z/7Z","to":7,"cm":0,"az":2.6732358,"al":0.544854,"lp":167,"ci":1,"cs":2},{"i":30129,"l":"4864.n1","iso":"4864.n","N":4864,"r":0,"t":"0","to":1,"cm":0,"az":2.7607998,"al":0.5629505,"lp":19,"ci":0,"cs":1},{"i":26088,"l":"4266.e1","iso":"4266.e","N":4266,"r":1,"t":"0","to":1,"cm":0,"az":2.7375269,"al":0.6387233,"lp":79,"ci":0,"cs":1},{"i":32326,"l":"5190.p1","iso":"5190.p","N":5190,"r":1,"t":"Z/2Z","to":2,"cm":0,"az":2.6906166,"al":0.5263658,"lp":173,"ci":0,"cs":2},{"i":32327,"l":"5190.p2","iso":"5190.p","N":5190,"r":1,"t":"Z/2Z","to":2,"cm":0,"az":2.6854417,"al":0.5224837,"lp":173,"ci":1,"cs":2},{"i":26896,"l":"4392.c1","iso":"4392.c","N":4392,"r":1,"t":"0","to":1,"cm":0,"az":2.647128,"al":0.6241567,"lp":61,"ci":0,"cs":1},{"i":30133,"l":"4865.b1","iso":"4865.b","N":4865,"r":1,"t":"0","to":1,"cm":0,"az":2.6866694,"al":0.5629376,"lp":139,"ci":0,"cs":1},{"i":26477,"l":"4326.c1","iso":"4326.c","N":4326,"r":1,"t":"0","to":1,"cm":0,"az":2.6864422,"al":0.6314691,"lp":103,"ci":0,"cs":1},{"i":30232,"l":"4890.c2","iso":"4890.c","N":4890,"r":0,"t":"Z/2Z \u00d7 Z/2Z","to":4,"cm":0,"az":2.6299842,"al":0.5612731,"lp":163,"ci":3,"cs":4},{"i":28703,"l":"4660.c1","iso":"4660.c","N":4660,"r":1,"t":"Z/2Z","to":2,"cm":0,"az":2.6426737,"al":0.5919374,"lp":233,"ci":0,"cs":2},{"i":28704,"l":"4660.c2","iso":"4660.c","N":4660,"r":1,"t":"Z/2Z","to":2,"cm":0,"az":2.6382805,"al":0.5884064,"lp":233,"ci":1,"cs":2},{"i":28150,"l":"4572.a1","iso":"4572.a","N":4572,"r":1,"t":"0","to":1,"cm":0,"az":2.7780968,"al":0.599285,"lp":127,"ci":0,"cs":2},{"i":26118,"l":"4270.g1","iso":"4270.g","N":4270,"r":0,"t":"0","to":1,"cm":0,"az":2.6716367,"al":0.63904,"lp":61,"ci":0,"cs":1},{"i":27429,"l":"4464.f1","iso":"4464.f","N":4464,"r":0,"t":"0","to":1,"cm":0,"az":2.7628141,"al":0.6142006,"lp":31,"ci":0,"cs":1},{"i":30940,"l":"4976.a1","iso":"4976.a","N":4976,"r":2,"t":"0","to":1,"cm":0,"az":2.7357497,"al":0.548525,"lp":311,"ci":0,"cs":1},{"i":30690,"l":"4947.d1","iso":"4947.d","N":4947,"r":0,"t":"0","to":1,"cm":0,"az":2.6878961,"al":0.5521974,"lp":97,"ci":0,"cs":1},{"i":29390,"l":"4770.bf1","iso":"4770.bf","N":4770,"r":0,"t":"0","to":1,"cm":0,"az":2.7136968,"al":0.5788371,"lp":53,"ci":0,"cs":1},{"i":31839,"l":"5126.e1","iso":"5126.e","N":5126,"r":1,"t":"0","to":1,"cm":0,"az":2.6964734,"al":0.5330762,"lp":233,"ci":0,"cs":1},{"i":31774,"l":"5110.c1","iso":"5110.c","N":5110,"r":0,"t":"0","to":1,"cm":0,"az":2.7596181,"al":0.533197,"lp":73,"ci":0,"cs":1},{"i":30231,"l":"4890.c1","iso":"4890.c","N":4890,"r":0,"t":"Z/2Z","to":2,"cm":0,"az":2.6288363,"al":0.5619915,"lp":163,"ci":0,"cs":4},{"i":30233,"l":"4890.c3","iso":"4890.c","N":4890,"r":0,"t":"Z/2Z","to":2,"cm":0,"az":2.6257266,"al":0.5631187,"lp":163,"ci":1,"cs":4},{"i":30234,"l":"4890.c4","iso":"4890.c","N":4890,"r":0,"t":"Z/2Z","to":2,"cm":0,"az":2.6244447,"al":0.560131,"lp":163,"ci":2,"cs":4},{"i":32315,"l":"5190.i1","iso":"5190.i","N":5190,"r":1,"t":"0","to":1,"cm":0,"az":2.6712377,"al":0.524657,"lp":173,"ci":0,"cs":1},{"i":26905,"l":"4393.a1","iso":"4393.a","N":4393,"r":0,"t":"0","to":1,"cm":0,"az":2.6833424,"al":0.6228658,"lp":191,"ci":0,"cs":1},{"i":29121,"l":"4722.e1","iso":"4722.e","N":4722,"r":1,"t":"Z/3Z","to":3,"cm":0,"az":2.622943,"al":0.5810873,"lp":787,"ci":1,"cs":2},{"i":26554,"l":"4338.f1","iso":"4338.f","N":4338,"r":1,"t":"0","to":1,"cm":0,"az":2.6371105,"al":0.6309063,"lp":241,"ci":0,"cs":1},{"i":28741,"l":"4665.b1","iso":"4665.b","N":4665,"r":1,"t":"0","to":1,"cm":0,"az":2.7070776,"al":0.588419,"lp":311,"ci":0,"cs":1},{"i":29766,"l":"4815.f1","iso":"4815.f","N":4815,"r":0,"t":"0","to":1,"cm":0,"az":2.7076386,"al":0.5695874,"lp":107,"ci":0,"cs":1},{"i":27728,"l":"4518.d1","iso":"4518.d","N":4518,"r":1,"t":"0","to":1,"cm":0,"az":2.693688,"al":0.6075415,"lp":251,"ci":0,"cs":1},{"i":27504,"l":"4475.c1","iso":"4475.c","N":4475,"r":0,"t":"0","to":1,"cm":0,"az":2.6549402,"al":0.6121374,"lp":179,"ci":0,"cs":1},{"i":26561,"l":"4342.b1","iso":"4342.b","N":4342,"r":0,"t":"0","to":1,"cm":0,"az":2.7305651,"al":0.631104,"lp":167,"ci":0,"cs":1},{"i":28474,"l":"4630.c2","iso":"4630.c","N":4630,"r":0,"t":"Z/3Z","to":3,"cm":0,"az":2.6923333,"al":0.5921801,"lp":463,"ci":1,"cs":2},{"i":26007,"l":"4239.c1","iso":"4239.c","N":4239,"r":0,"t":"0","to":1,"cm":0,"az":2.6607255,"al":0.6416327,"lp":157,"ci":0,"cs":1},{"i":26415,"l":"4310.a1","iso":"4310.a","N":4310,"r":1,"t":"0","to":1,"cm":0,"az":2.6626349,"al":0.6341914,"lp":431,"ci":0,"cs":1},{"i":28381,"l":"4610.b1","iso":"4610.b","N":4610,"r":1,"t":"0","to":1,"cm":0,"az":2.7539362,"al":0.5955166,"lp":461,"ci":0,"cs":1},{"i":28157,"l":"4572.f1","iso":"4572.f","N":4572,"r":0,"t":"0","to":1,"cm":0,"az":2.7338075,"al":0.5990646,"lp":127,"ci":0,"cs":1},{"i":30921,"l":"4971.a1","iso":"4971.a","N":4971,"r":2,"t":"0","to":1,"cm":0,"az":2.7412194,"al":0.5496192,"lp":1657,"ci":0,"cs":1},{"i":30673,"l":"4944.g1","iso":"4944.g","N":4944,"r":0,"t":"0","to":1,"cm":0,"az":2.789284,"al":0.5543926,"lp":103,"ci":0,"cs":1},{"i":31836,"l":"5126.b1","iso":"5126.b","N":5126,"r":0,"t":"0","to":1,"cm":0,"az":2.7211218,"al":0.5321647,"lp":233,"ci":0,"cs":1},{"i":31490,"l":"5068.c1","iso":"5068.c","N":5068,"r":0,"t":"0","to":1,"cm":0,"az":2.6539178,"al":0.5386506,"lp":181,"ci":0,"cs":1},{"i":26988,"l":"4404.g1","iso":"4404.g","N":4404,"r":0,"t":"Z/2Z","to":2,"cm":0,"az":2.7843562,"al":0.6225385,"lp":367,"ci":0,"cs":2},{"i":26989,"l":"4404.g2","iso":"4404.g","N":4404,"r":0,"t":"Z/2Z","to":2,"cm":0,"az":2.7808564,"al":0.6205236,"lp":367,"ci":1,"cs":2},{"i":26740,"l":"4367.a1","iso":"4367.a","N":4367,"r":0,"t":"0","to":1,"cm":0,"az":2.7772425,"al":0.6266131,"lp":397,"ci":0,"cs":1},{"i":29125,"l":"4722.h1","iso":"4722.h","N":4722,"r":1,"t":"0","to":1,"cm":0,"az":2.6815834,"al":0.5831583,"lp":787,"ci":0,"cs":1},{"i":30662,"l":"4942.d1","iso":"4942.d","N":4942,"r":0,"t":"0","to":1,"cm":0,"az":2.6872416,"al":0.5545636,"lp":353,"ci":0,"cs":1},{"i":30183,"l":"4878.f1","iso":"4878.f","N":4878,"r":0,"t":"0","to":1,"cm":0,"az":2.6308788,"al":0.5615742,"lp":271,"ci":0,"cs":1},{"i":31924,"l":"5142.d1","iso":"5142.d","N":5142,"r":1,"t":"0","to":1,"cm":0,"az":2.7409094,"al":0.5304626,"lp":857,"ci":0,"cs":1},{"i":26710,"l":"4357.a1","iso":"4357.a","N":4357,"r":2,"t":"0","to":1,"cm":0,"az":2.6826906,"al":0.626775,"lp":4357,"ci":0,"cs":1},{"i":31124,"l":"5013.a1","iso":"5013.a","N":5013,"r":0,"t":"0","to":1,"cm":0,"az":2.7911989,"al":0.5465609,"lp":557,"ci":0,"cs":1},{"i":30975,"l":"4990.a1","iso":"4990.a","N":4990,"r":0,"t":"0","to":1,"cm":0,"az":2.6905222,"al":0.5473915,"lp":499,"ci":0,"cs":1},{"i":27929,"l":"4552.a1","iso":"4552.a","N":4552,"r":0,"t":"0","to":1,"cm":0,"az":2.7485634,"al":0.6053212,"lp":569,"ci":0,"cs":1},{"i":27410,"l":"4458.b1","iso":"4458.b","N":4458,"r":0,"t":"0","to":1,"cm":0,"az":2.6460734,"al":0.6139462,"lp":743,"ci":0,"cs":1},{"i":26170,"l":"4276.a1","iso":"4276.a","N":4276,"r":0,"t":"0","to":1,"cm":0,"az":2.6790739,"al":0.638071,"lp":1069,"ci":0,"cs":1},{"i":31212,"l":"5036.a1","iso":"5036.a","N":5036,"r":0,"t":"0","to":1,"cm":0,"az":2.7105591,"al":0.5436388,"lp":1259,"ci":0,"cs":1},{"i":29430,"l":"4778.a1","iso":"4778.a","N":4778,"r":0,"t":"0","to":1,"cm":0,"az":2.7722851,"al":0.5763632,"lp":2389,"ci":0,"cs":1}]}