{"tile":"a24_q06","points":[{"i":45178,"l":"7056.bb2","iso":"7056.bb","N":7056,"r":1,"t":"Z/2Z","to":2,"cm":1,"az":4.1908966,"al":0.3083825,"lp":7,"ci":1,"cs":4},{"i":45180,"l":"7056.bb4","iso":"7056.bb","N":7056,"r":1,"t":"Z/2Z","to":2,"cm":1,"az":4.1951397,"al":0.3060039,"lp":7,"ci":3,"cs":4},{"i":40519,"l":"6400.a1","iso":"6400.a","N":6400,"r":0,"t":"Z/2Z","to":2,"cm":1,"az":4.2158487,"al":0.3842451,"lp":5,"ci":0,"cs":2},{"i":40520,"l":"6400.a2","iso":"6400.a","N":6400,"r":0,"t":"Z/2Z","to":2,"cm":1,"az":4.2111527,"al":0.3811063,"lp":5,"ci":1,"cs":2},{"i":45173,"l":"7056.z1","iso":"7056.z","N":7056,"r":1,"t":"0","to":1,"cm":1,"az":4.3053385,"al":0.3056217,"lp":7,"ci":0,"cs":2},{"i":45171,"l":"7056.y1","iso":"7056.y","N":7056,"r":0,"t":"0","to":1,"cm":1,"az":4.2537908,"al":0.3075809,"lp":7,"ci":0,"cs":2},{"i":45172,"l":"7056.y2","iso":"7056.y","N":7056,"r":0,"t":"0","to":1,"cm":1,"az":4.2476212,"al":0.3067905,"lp":7,"ci":1,"cs":2},{"i":42207,"l":"6630.v6","iso":"6630.v","N":6630,"r":1,"t":"Z/2Z \u00d7 Z/6Z","to":12,"cm":0,"az":4.2992443,"al":0.3579365,"lp":17,"ci":6,"cs":8},{"i":42208,"l":"6630.v7","iso":"6630.v","N":6630,"r":1,"t":"Z/12Z","to":12,"cm":0,"az":4.3009568,"al":0.3543754,"lp":17,"ci":7,"cs":8},{"i":40804,"l":"6435.f2","iso":"6435.f","N":6435,"r":1,"t":"Z/2Z \u00d7 Z/2Z","to":4,"cm":0,"az":4.3112165,"al":0.3754538,"lp":13,"ci":2,"cs":4},{"i":40805,"l":"6435.f3","iso":"6435.f","N":6435,"r":1,"t":"Z/4Z","to":4,"cm":0,"az":4.3091586,"al":0.3781174,"lp":13,"ci":3,"cs":4},{"i":42205,"l":"6630.v4","iso":"6630.v","N":6630,"r":1,"t":"Z/6Z","to":6,"cm":0,"az":4.2994525,"al":0.3527865,"lp":17,"ci":4,"cs":8},{"i":42209,"l":"6630.v8","iso":"6630.v","N":6630,"r":1,"t":"Z/6Z","to":6,"cm":0,"az":4.3008182,"al":0.3525273,"lp":17,"ci":5,"cs":8},{"i":42874,"l":"6720.by1","iso":"6720.by","N":6720,"r":1,"t":"Z/4Z","to":4,"cm":0,"az":4.25397,"al":0.3430357,"lp":7,"ci":2,"cs":4},{"i":42875,"l":"6720.by2","iso":"6720.by","N":6720,"r":1,"t":"Z/2Z \u00d7 Z/2Z","to":4,"cm":0,"az":4.2572443,"al":0.3453105,"lp":7,"ci":3,"cs":4},{"i":40803,"l":"6435.f1","iso":"6435.f","N":6435,"r":1,"t":"Z/2Z","to":2,"cm":0,"az":4.3113517,"al":0.3808055,"lp":13,"ci":0,"cs":4},{"i":40806,"l":"6435.f4","iso":"6435.f","N":6435,"r":1,"t":"Z/2Z","to":2,"cm":0,"az":4.3063632,"al":0.3801923,"lp":13,"ci":1,"cs":4},{"i":38971,"l":"6188.c1","iso":"6188.c","N":6188,"r":1,"t":"Z/3Z","to":3,"cm":0,"az":4.3435537,"al":0.406418,"lp":17,"ci":1,"cs":2},{"i":44616,"l":"6970.a1","iso":"6970.a","N":6970,"r":2,"t":"Z/2Z","to":2,"cm":0,"az":4.2430869,"al":0.3174274,"lp":41,"ci":0,"cs":2},{"i":44617,"l":"6970.a2","iso":"6970.a","N":6970,"r":2,"t":"Z/2Z","to":2,"cm":0,"az":4.2363265,"al":0.3152633,"lp":41,"ci":1,"cs":2},{"i":39822,"l":"6318.g2","iso":"6318.g","N":6318,"r":1,"t":"Z/3Z","to":3,"cm":0,"az":4.3232809,"al":0.3929074,"lp":13,"ci":1,"cs":2},{"i":42876,"l":"6720.by3","iso":"6720.by","N":6720,"r":1,"t":"Z/2Z","to":2,"cm":0,"az":4.2571495,"al":0.3453668,"lp":7,"ci":0,"cs":4},{"i":42877,"l":"6720.by4","iso":"6720.by","N":6720,"r":1,"t":"Z/2Z","to":2,"cm":0,"az":4.2559056,"al":0.3484745,"lp":7,"ci":1,"cs":4},{"i":41134,"l":"6480.t1","iso":"6480.t","N":6480,"r":1,"t":"0","to":1,"cm":0,"az":4.2811434,"al":0.3743138,"lp":5,"ci":0,"cs":2},{"i":41135,"l":"6480.t2","iso":"6480.t","N":6480,"r":1,"t":"0","to":1,"cm":0,"az":4.2764985,"al":0.3742022,"lp":5,"ci":1,"cs":2},{"i":41266,"l":"6498.h1","iso":"6498.h","N":6498,"r":1,"t":"Z/2Z","to":2,"cm":0,"az":4.3572259,"al":0.3715307,"lp":19,"ci":0,"cs":2},{"i":41267,"l":"6498.h2","iso":"6498.h","N":6498,"r":1,"t":"Z/2Z","to":2,"cm":0,"az":4.3553205,"al":0.3701076,"lp":19,"ci":1,"cs":2},{"i":44145,"l":"6916.a1","iso":"6916.a","N":6916,"r":2,"t":"0","to":1,"cm":0,"az":4.2206784,"al":0.3228515,"lp":19,"ci":0,"cs":1},{"i":44121,"l":"6912.p1","iso":"6912.p","N":6912,"r":0,"t":"0","to":1,"cm":0,"az":4.2983341,"al":0.3226615,"lp":3,"ci":0,"cs":1},{"i":40431,"l":"6384.bf2","iso":"6384.bf","N":6384,"r":1,"t":"Z/2Z \u00d7 Z/2Z","to":4,"cm":0,"az":4.3195509,"al":0.3867025,"lp":19,"ci":3,"cs":4},{"i":45129,"l":"7056.g2","iso":"7056.g","N":7056,"r":1,"t":"0","to":1,"cm":0,"az":4.254313,"al":0.3055909,"lp":7,"ci":1,"cs":2},{"i":39533,"l":"6270.o1","iso":"6270.o","N":6270,"r":1,"t":"Z/2Z","to":2,"cm":0,"az":4.2479925,"al":0.4009568,"lp":19,"ci":0,"cs":2},{"i":39534,"l":"6270.o2","iso":"6270.o","N":6270,"r":1,"t":"Z/2Z","to":2,"cm":0,"az":4.2463779,"al":0.3996611,"lp":19,"ci":1,"cs":2},{"i":40279,"l":"6370.i1","iso":"6370.i","N":6370,"r":1,"t":"0","to":1,"cm":0,"az":4.3481074,"al":0.3864405,"lp":13,"ci":0,"cs":2},{"i":40280,"l":"6370.i2","iso":"6370.i","N":6370,"r":1,"t":"0","to":1,"cm":0,"az":4.343176,"al":0.3870801,"lp":13,"ci":1,"cs":2},{"i":39657,"l":"6292.e1","iso":"6292.e","N":6292,"r":1,"t":"0","to":1,"cm":0,"az":4.3420951,"al":0.3976971,"lp":13,"ci":0,"cs":1},{"i":43984,"l":"6890.m2","iso":"6890.m","N":6890,"r":1,"t":"Z/2Z \u00d7 Z/2Z","to":4,"cm":0,"az":4.2102181,"al":0.324722,"lp":53,"ci":1,"cs":4},{"i":43985,"l":"6890.m3","iso":"6890.m","N":6890,"r":1,"t":"Z/4Z","to":4,"cm":0,"az":4.2082538,"al":0.3223288,"lp":53,"ci":2,"cs":4},{"i":43986,"l":"6890.m4","iso":"6890.m","N":6890,"r":1,"t":"Z/4Z","to":4,"cm":0,"az":4.2110839,"al":0.3238053,"lp":53,"ci":3,"cs":4},{"i":42158,"l":"6630.b3","iso":"6630.b","N":6630,"r":0,"t":"Z/2Z \u00d7 Z/2Z","to":4,"cm":0,"az":4.3348427,"al":0.3563556,"lp":17,"ci":3,"cs":4},{"i":39292,"l":"6237.c1","iso":"6237.c","N":6237,"r":1,"t":"0","to":1,"cm":0,"az":4.35444,"al":0.4037173,"lp":11,"ci":0,"cs":1},{"i":43249,"l":"6783.d1","iso":"6783.d","N":6783,"r":1,"t":"0","to":1,"cm":0,"az":4.3102942,"al":0.3367419,"lp":19,"ci":0,"cs":2},{"i":41664,"l":"6552.v2","iso":"6552.v","N":6552,"r":0,"t":"Z/2Z \u00d7 Z/2Z","to":4,"cm":0,"az":4.2682339,"al":0.3616664,"lp":13,"ci":3,"cs":6},{"i":41667,"l":"6552.v5","iso":"6552.v","N":6552,"r":0,"t":"Z/2Z \u00d7 Z/2Z","to":4,"cm":0,"az":4.2685037,"al":0.3624296,"lp":13,"ci":4,"cs":6},{"i":41668,"l":"6552.v6","iso":"6552.v","N":6552,"r":0,"t":"Z/4Z","to":4,"cm":0,"az":4.2663564,"al":0.3635102,"lp":13,"ci":5,"cs":6},{"i":45222,"l":"7056.bu1","iso":"7056.bu","N":7056,"r":0,"t":"Z/2Z","to":2,"cm":0,"az":4.2365192,"al":0.3088225,"lp":7,"ci":0,"cs":2},{"i":45223,"l":"7056.bu2","iso":"7056.bu","N":7056,"r":0,"t":"Z/2Z","to":2,"cm":0,"az":4.2321931,"al":0.3054519,"lp":7,"ci":1,"cs":2},{"i":44896,"l":"7021.a1","iso":"7021.a","N":7021,"r":2,"t":"0","to":1,"cm":0,"az":4.2518035,"al":0.311305,"lp":59,"ci":0,"cs":1},{"i":42576,"l":"6699.d2","iso":"6699.d","N":6699,"r":0,"t":"Z/2Z \u00d7 Z/2Z","to":4,"cm":0,"az":4.2887576,"al":0.3501535,"lp":29,"ci":3,"cs":4},{"i":39405,"l":"6253.b1","iso":"6253.b","N":6253,"r":1,"t":"0","to":1,"cm":0,"az":4.3084913,"al":0.4004785,"lp":37,"ci":0,"cs":3},{"i":39882,"l":"6325.g1","iso":"6325.g","N":6325,"r":1,"t":"0","to":1,"cm":0,"az":4.3019309,"al":0.3949269,"lp":23,"ci":0,"cs":1},{"i":39358,"l":"6240.x3","iso":"6240.x","N":6240,"r":0,"t":"Z/2Z \u00d7 Z/2Z","to":4,"cm":0,"az":4.279287,"al":0.4037264,"lp":13,"ci":3,"cs":4},{"i":40430,"l":"6384.bf1","iso":"6384.bf","N":6384,"r":1,"t":"Z/2Z","to":2,"cm":0,"az":4.3195867,"al":0.3860651,"lp":19,"ci":0,"cs":4},{"i":40432,"l":"6384.bf3","iso":"6384.bf","N":6384,"r":1,"t":"Z/2Z","to":2,"cm":0,"az":4.3144178,"al":0.388267,"lp":19,"ci":1,"cs":4},{"i":40433,"l":"6384.bf4","iso":"6384.bf","N":6384,"r":1,"t":"Z/2Z","to":2,"cm":0,"az":4.3162018,"al":0.3825183,"lp":19,"ci":2,"cs":4},{"i":43189,"l":"6771.a1","iso":"6771.a","N":6771,"r":1,"t":"Z/2Z","to":2,"cm":0,"az":4.2523801,"al":0.3383992,"lp":61,"ci":0,"cs":2},{"i":43190,"l":"6771.a2","iso":"6771.a","N":6771,"r":1,"t":"Z/2Z","to":2,"cm":0,"az":4.2519772,"al":0.3372728,"lp":61,"ci":1,"cs":2},{"i":39824,"l":"6318.h2","iso":"6318.h","N":6318,"r":0,"t":"Z/3Z","to":3,"cm":0,"az":4.2166311,"al":0.3939483,"lp":13,"ci":1,"cs":2},{"i":40420,"l":"6384.ba1","iso":"6384.ba","N":6384,"r":1,"t":"Z/2Z","to":2,"cm":0,"az":4.2724722,"al":0.3855475,"lp":19,"ci":0,"cs":2},{"i":40421,"l":"6384.ba2","iso":"6384.ba","N":6384,"r":1,"t":"Z/2Z","to":2,"cm":0,"az":4.2734629,"al":0.3830143,"lp":19,"ci":1,"cs":2},{"i":43722,"l":"6845.b1","iso":"6845.b","N":6845,"r":1,"t":"0","to":1,"cm":0,"az":4.3093819,"al":0.3288153,"lp":37,"ci":0,"cs":1},{"i":39821,"l":"6318.g1","iso":"6318.g","N":6318,"r":1,"t":"0","to":1,"cm":0,"az":4.3221667,"al":0.3957512,"lp":13,"ci":0,"cs":2},{"i":42365,"l":"6660.e2","iso":"6660.e","N":6660,"r":1,"t":"Z/3Z","to":3,"cm":0,"az":4.2050155,"al":0.3509579,"lp":37,"ci":1,"cs":2},{"i":41175,"l":"6486.j1","iso":"6486.j","N":6486,"r":1,"t":"Z/2Z","to":2,"cm":0,"az":4.3307768,"al":0.3731778,"lp":47,"ci":0,"cs":2},{"i":41176,"l":"6486.j2","iso":"6486.j","N":6486,"r":1,"t":"Z/2Z","to":2,"cm":0,"az":4.3263982,"al":0.3719423,"lp":47,"ci":1,"cs":2},{"i":40972,"l":"6460.b1","iso":"6460.b","N":6460,"r":1,"t":"0","to":1,"cm":0,"az":4.1927154,"al":0.3760175,"lp":19,"ci":0,"cs":1},{"i":42301,"l":"6650.i1","iso":"6650.i","N":6650,"r":1,"t":"0","to":1,"cm":0,"az":4.3015332,"al":0.3540807,"lp":19,"ci":0,"cs":1},{"i":41258,"l":"6498.d1","iso":"6498.d","N":6498,"r":0,"t":"Z/2Z","to":2,"cm":0,"az":4.2477495,"al":0.3719074,"lp":19,"ci":0,"cs":2},{"i":41259,"l":"6498.d2","iso":"6498.d","N":6498,"r":0,"t":"Z/2Z","to":2,"cm":0,"az":4.2462009,"al":0.3702551,"lp":19,"ci":1,"cs":2},{"i":43983,"l":"6890.m1","iso":"6890.m","N":6890,"r":1,"t":"Z/2Z","to":2,"cm":0,"az":4.2107397,"al":0.3261501,"lp":53,"ci":0,"cs":4},{"i":43943,"l":"6885.b1","iso":"6885.b","N":6885,"r":1,"t":"0","to":1,"cm":0,"az":4.3110142,"al":0.3253432,"lp":17,"ci":0,"cs":1},{"i":44346,"l":"6936.l1","iso":"6936.l","N":6936,"r":1,"t":"0","to":1,"cm":0,"az":4.2451919,"al":0.3191299,"lp":17,"ci":0,"cs":1},{"i":40444,"l":"6390.b3","iso":"6390.b","N":6390,"r":1,"t":"Z/2Z \u00d7 Z/2Z","to":4,"cm":0,"az":4.2260473,"al":0.3847669,"lp":71,"ci":3,"cs":4},{"i":42156,"l":"6630.b1","iso":"6630.b","N":6630,"r":0,"t":"Z/2Z","to":2,"cm":0,"az":4.3352769,"al":0.3553313,"lp":17,"ci":0,"cs":4},{"i":42157,"l":"6630.b2","iso":"6630.b","N":6630,"r":0,"t":"Z/2Z","to":2,"cm":0,"az":4.3320131,"al":0.3579182,"lp":17,"ci":1,"cs":4},{"i":42159,"l":"6630.b4","iso":"6630.b","N":6630,"r":0,"t":"Z/2Z","to":2,"cm":0,"az":4.3298237,"al":0.3554228,"lp":17,"ci":2,"cs":4},{"i":40083,"l":"6336.cl1","iso":"6336.cl","N":6336,"r":0,"t":"Z/2Z","to":2,"cm":0,"az":4.1977903,"al":0.3937637,"lp":11,"ci":0,"cs":2},{"i":40084,"l":"6336.cl2","iso":"6336.cl","N":6336,"r":0,"t":"Z/2Z","to":2,"cm":0,"az":4.1972438,"al":0.3913304,"lp":11,"ci":1,"cs":2},{"i":41986,"l":"6600.j1","iso":"6600.j","N":6600,"r":0,"t":"Z/2Z","to":2,"cm":0,"az":4.29666,"al":0.3584064,"lp":11,"ci":0,"cs":2},{"i":41987,"l":"6600.j2","iso":"6600.j","N":6600,"r":0,"t":"Z/2Z","to":2,"cm":0,"az":4.2940668,"al":0.3557613,"lp":11,"ci":1,"cs":2},{"i":42150,"l":"6627.i1","iso":"6627.i","N":6627,"r":1,"t":"0","to":1,"cm":0,"az":4.3225303,"al":0.3560597,"lp":47,"ci":0,"cs":1},{"i":41376,"l":"6510.ba3","iso":"6510.ba","N":6510,"r":0,"t":"Z/2Z \u00d7 Z/2Z","to":4,"cm":0,"az":4.2117651,"al":0.3683491,"lp":31,"ci":2,"cs":4},{"i":41377,"l":"6510.ba4","iso":"6510.ba","N":6510,"r":0,"t":"Z/4Z","to":4,"cm":0,"az":4.2109116,"al":0.3670538,"lp":31,"ci":3,"cs":4},{"i":42570,"l":"6699.b1","iso":"6699.b","N":6699,"r":1,"t":"0","to":1,"cm":0,"az":4.3009479,"al":0.3478776,"lp":29,"ci":0,"cs":1},{"i":41663,"l":"6552.v1","iso":"6552.v","N":6552,"r":0,"t":"Z/2Z","to":2,"cm":0,"az":4.2667413,"al":0.3658825,"lp":13,"ci":0,"cs":6},{"i":41665,"l":"6552.v3","iso":"6552.v","N":6552,"r":0,"t":"Z/2Z","to":2,"cm":0,"az":4.2667446,"al":0.365484,"lp":13,"ci":1,"cs":6},{"i":41666,"l":"6552.v4","iso":"6552.v","N":6552,"r":0,"t":"Z/2Z","to":2,"cm":0,"az":4.2650102,"al":0.3650341,"lp":13,"ci":2,"cs":6},{"i":42575,"l":"6699.d1","iso":"6699.d","N":6699,"r":0,"t":"Z/2Z","to":2,"cm":0,"az":4.2889259,"al":0.3506728,"lp":29,"ci":0,"cs":4},{"i":42577,"l":"6699.d3","iso":"6699.d","N":6699,"r":0,"t":"Z/2Z","to":2,"cm":0,"az":4.2843912,"al":0.351879,"lp":29,"ci":1,"cs":4},{"i":42578,"l":"6699.d4","iso":"6699.d","N":6699,"r":0,"t":"Z/2Z","to":2,"cm":0,"az":4.2849698,"al":0.3462006,"lp":29,"ci":2,"cs":4},{"i":44437,"l":"6954.m1","iso":"6954.m","N":6954,"r":1,"t":"Z/2Z","to":2,"cm":0,"az":4.2095132,"al":0.3194729,"lp":61,"ci":0,"cs":2},{"i":44438,"l":"6954.m2","iso":"6954.m","N":6954,"r":1,"t":"Z/2Z","to":2,"cm":0,"az":4.2064062,"al":0.318193,"lp":61,"ci":1,"cs":2},{"i":39856,"l":"6321.c1","iso":"6321.c","N":6321,"r":1,"t":"0","to":1,"cm":0,"az":4.2283737,"al":0.3950346,"lp":43,"ci":0,"cs":3},{"i":39106,"l":"6206.a1","iso":"6206.a","N":6206,"r":2,"t":"0","to":1,"cm":0,"az":4.3216476,"al":0.406748,"lp":107,"ci":0,"cs":1},{"i":44932,"l":"7030.h2","iso":"7030.h","N":7030,"r":1,"t":"0","to":1,"cm":0,"az":4.32569,"al":0.309659,"lp":37,"ci":0,"cs":2},{"i":39421,"l":"6256.d1","iso":"6256.d","N":6256,"r":1,"t":"0","to":1,"cm":0,"az":4.3300855,"al":0.400248,"lp":23,"ci":0,"cs":1},{"i":39356,"l":"6240.x1","iso":"6240.x","N":6240,"r":0,"t":"Z/2Z","to":2,"cm":0,"az":4.2788926,"al":0.4034786,"lp":13,"ci":0,"cs":4},{"i":39357,"l":"6240.x2","iso":"6240.x","N":6240,"r":0,"t":"Z/2Z","to":2,"cm":0,"az":4.2764912,"al":0.4048826,"lp":13,"ci":1,"cs":4},{"i":39359,"l":"6240.x4","iso":"6240.x","N":6240,"r":0,"t":"Z/2Z","to":2,"cm":0,"az":4.2727773,"al":0.4015313,"lp":13,"ci":2,"cs":4},{"i":41706,"l":"6557.b1","iso":"6557.b","N":6557,"r":1,"t":"0","to":1,"cm":0,"az":4.3026545,"al":0.3627918,"lp":83,"ci":0,"cs":1},{"i":39136,"l":"6210.n1","iso":"6210.n","N":6210,"r":1,"t":"0","to":1,"cm":0,"az":4.2342346,"al":0.4047348,"lp":23,"ci":0,"cs":1},{"i":39800,"l":"6314.e1","iso":"6314.e","N":6314,"r":1,"t":"0","to":1,"cm":0,"az":4.2332509,"al":0.3948465,"lp":41,"ci":0,"cs":1},{"i":39104,"l":"6205.b2","iso":"6205.b","N":6205,"r":0,"t":"Z/3Z","to":3,"cm":0,"az":4.1906289,"al":0.4053215,"lp":73,"ci":1,"cs":2},{"i":44416,"l":"6952.a1","iso":"6952.a","N":6952,"r":2,"t":"0","to":1,"cm":0,"az":4.2732314,"al":0.3182056,"lp":79,"ci":0,"cs":1},{"i":41488,"l":"6528.n1","iso":"6528.n","N":6528,"r":0,"t":"Z/2Z","to":2,"cm":0,"az":4.2787569,"al":0.3689126,"lp":17,"ci":0,"cs":2},{"i":41489,"l":"6528.n2","iso":"6528.n","N":6528,"r":0,"t":"Z/2Z","to":2,"cm":0,"az":4.2757331,"al":0.3656564,"lp":17,"ci":1,"cs":2},{"i":40442,"l":"6390.b1","iso":"6390.b","N":6390,"r":1,"t":"Z/2Z","to":2,"cm":0,"az":4.2250012,"al":0.386523,"lp":71,"ci":0,"cs":4},{"i":40443,"l":"6390.b2","iso":"6390.b","N":6390,"r":1,"t":"Z/2Z","to":2,"cm":0,"az":4.2217746,"al":0.3848174,"lp":71,"ci":1,"cs":4},{"i":40445,"l":"6390.b4","iso":"6390.b","N":6390,"r":1,"t":"Z/2Z","to":2,"cm":0,"az":4.2191854,"al":0.382062,"lp":71,"ci":2,"cs":4},{"i":39598,"l":"6283.b1","iso":"6283.b","N":6283,"r":1,"t":"0","to":1,"cm":0,"az":4.2810382,"al":0.3994286,"lp":103,"ci":0,"cs":1},{"i":41374,"l":"6510.ba1","iso":"6510.ba","N":6510,"r":0,"t":"Z/2Z","to":2,"cm":0,"az":4.2120089,"al":0.3699614,"lp":31,"ci":0,"cs":4},{"i":41375,"l":"6510.ba2","iso":"6510.ba","N":6510,"r":0,"t":"Z/2Z","to":2,"cm":0,"az":4.2081998,"al":0.3721756,"lp":31,"ci":1,"cs":4},{"i":41385,"l":"6510.bd1","iso":"6510.bd","N":6510,"r":0,"t":"Z/2Z","to":2,"cm":0,"az":4.1988776,"al":0.3689293,"lp":31,"ci":0,"cs":4},{"i":41386,"l":"6510.bd2","iso":"6510.bd","N":6510,"r":0,"t":"Z/2Z","to":2,"cm":0,"az":4.1974627,"al":0.3696736,"lp":31,"ci":1,"cs":4},{"i":41855,"l":"6574.b1","iso":"6574.b","N":6574,"r":2,"t":"0","to":1,"cm":0,"az":4.300238,"al":0.3599558,"lp":173,"ci":0,"cs":1},{"i":42657,"l":"6715.f1","iso":"6715.f","N":6715,"r":1,"t":"0","to":1,"cm":0,"az":4.3525455,"al":0.3478234,"lp":79,"ci":0,"cs":1},{"i":40975,"l":"6460.d1","iso":"6460.d","N":6460,"r":0,"t":"0","to":1,"cm":0,"az":4.2061828,"al":0.3743577,"lp":19,"ci":0,"cs":1},{"i":42364,"l":"6660.e1","iso":"6660.e","N":6660,"r":1,"t":"0","to":1,"cm":0,"az":4.2111041,"al":0.3527807,"lp":37,"ci":0,"cs":2},{"i":45282,"l":"7062.m1","iso":"7062.m","N":7062,"r":1,"t":"Z/2Z","to":2,"cm":0,"az":4.3407114,"al":0.3064823,"lp":107,"ci":0,"cs":2},{"i":45283,"l":"7062.m2","iso":"7062.m","N":7062,"r":1,"t":"Z/2Z","to":2,"cm":0,"az":4.3374131,"al":0.3025048,"lp":107,"ci":1,"cs":2},{"i":43947,"l":"6885.e1","iso":"6885.e","N":6885,"r":0,"t":"0","to":1,"cm":0,"az":4.355583,"al":0.3250139,"lp":17,"ci":0,"cs":1},{"i":41768,"l":"6566.c1","iso":"6566.c","N":6566,"r":1,"t":"0","to":1,"cm":0,"az":4.3243888,"al":0.3622753,"lp":67,"ci":0,"cs":1},{"i":42237,"l":"6633.i1","iso":"6633.i","N":6633,"r":1,"t":"0","to":1,"cm":0,"az":4.1971071,"al":0.3557168,"lp":67,"ci":0,"cs":1},{"i":45081,"l":"7050.v1","iso":"7050.v","N":7050,"r":1,"t":"0","to":1,"cm":0,"az":4.3574216,"al":0.3065231,"lp":47,"ci":0,"cs":1},{"i":41671,"l":"6552.y1","iso":"6552.y","N":6552,"r":0,"t":"0","to":1,"cm":0,"az":4.3205262,"al":0.3639545,"lp":13,"ci":0,"cs":1},{"i":42976,"l":"6728.c1","iso":"6728.c","N":6728,"r":0,"t":"0","to":1,"cm":0,"az":4.3327195,"al":0.3407464,"lp":29,"ci":0,"cs":1},{"i":44489,"l":"6960.j1","iso":"6960.j","N":6960,"r":0,"t":"Z/2Z","to":2,"cm":0,"az":4.3457515,"al":0.3167051,"lp":29,"ci":0,"cs":2},{"i":44490,"l":"6960.j2","iso":"6960.j","N":6960,"r":0,"t":"Z/2Z","to":2,"cm":0,"az":4.3455528,"al":0.3168844,"lp":29,"ci":1,"cs":2},{"i":43404,"l":"6800.q1","iso":"6800.q","N":6800,"r":0,"t":"0","to":1,"cm":0,"az":4.2895732,"al":0.3344483,"lp":17,"ci":0,"cs":1},{"i":44947,"l":"7035.g1","iso":"7035.g","N":7035,"r":0,"t":"Z/2Z","to":2,"cm":0,"az":4.2759316,"al":0.3111364,"lp":67,"ci":0,"cs":2},{"i":44948,"l":"7035.g2","iso":"7035.g","N":7035,"r":0,"t":"Z/2Z","to":2,"cm":0,"az":4.2730455,"al":0.3086233,"lp":67,"ci":1,"cs":2},{"i":42480,"l":"6678.o1","iso":"6678.o","N":6678,"r":0,"t":"Z/2Z","to":2,"cm":0,"az":4.2588291,"al":0.3504086,"lp":53,"ci":0,"cs":2},{"i":42481,"l":"6678.o2","iso":"6678.o","N":6678,"r":0,"t":"Z/2Z","to":2,"cm":0,"az":4.2524912,"al":0.35005,"lp":53,"ci":1,"cs":2},{"i":42075,"l":"6613.a1","iso":"6613.a","N":6613,"r":2,"t":"0","to":1,"cm":0,"az":4.3393137,"al":0.3581498,"lp":389,"ci":0,"cs":1},{"i":43501,"l":"6811.k1","iso":"6811.k","N":6811,"r":1,"t":"0","to":1,"cm":0,"az":4.2116518,"al":0.3332506,"lp":139,"ci":0,"cs":1},{"i":39017,"l":"6192.s1","iso":"6192.s","N":6192,"r":1,"t":"0","to":1,"cm":0,"az":4.3385116,"al":0.4079769,"lp":43,"ci":0,"cs":1},{"i":41959,"l":"6596.b1","iso":"6596.b","N":6596,"r":1,"t":"0","to":1,"cm":0,"az":4.3329606,"al":0.3576991,"lp":97,"ci":0,"cs":1},{"i":43923,"l":"6880.e1","iso":"6880.e","N":6880,"r":1,"t":"0","to":1,"cm":0,"az":4.3121915,"al":0.3273435,"lp":43,"ci":0,"cs":1},{"i":40320,"l":"6372.b1","iso":"6372.b","N":6372,"r":1,"t":"0","to":1,"cm":0,"az":4.3421059,"al":0.3874684,"lp":59,"ci":0,"cs":1},{"i":43351,"l":"6798.b1","iso":"6798.b","N":6798,"r":1,"t":"0","to":1,"cm":0,"az":4.2268205,"al":0.3368743,"lp":103,"ci":0,"cs":1},{"i":43163,"l":"6768.h1","iso":"6768.h","N":6768,"r":0,"t":"Z/2Z","to":2,"cm":0,"az":4.218858,"al":0.3416132,"lp":47,"ci":0,"cs":2},{"i":43164,"l":"6768.h2","iso":"6768.h","N":6768,"r":0,"t":"Z/2Z","to":2,"cm":0,"az":4.2176538,"al":0.3375576,"lp":47,"ci":1,"cs":2},{"i":40941,"l":"6450.ba1","iso":"6450.ba","N":6450,"r":0,"t":"0","to":1,"cm":0,"az":4.2648943,"al":0.3773669,"lp":43,"ci":0,"cs":2},{"i":40603,"l":"6402.t1","iso":"6402.t","N":6402,"r":0,"t":"Z/2Z","to":2,"cm":0,"az":4.3400349,"al":0.3821583,"lp":97,"ci":0,"cs":2},{"i":40604,"l":"6402.t2","iso":"6402.t","N":6402,"r":0,"t":"Z/2Z","to":2,"cm":0,"az":4.3385375,"al":0.3813531,"lp":97,"ci":1,"cs":2},{"i":39605,"l":"6286.c2","iso":"6286.c","N":6286,"r":1,"t":"Z/3Z","to":3,"cm":0,"az":4.2851496,"al":0.3957071,"lp":449,"ci":1,"cs":2},{"i":41857,"l":"6574.d1","iso":"6574.d","N":6574,"r":1,"t":"0","to":1,"cm":0,"az":4.3574867,"al":0.3616584,"lp":173,"ci":0,"cs":1},{"i":40959,"l":"6450.bl1","iso":"6450.bl","N":6450,"r":0,"t":"0","to":1,"cm":0,"az":4.294842,"al":0.3749919,"lp":43,"ci":0,"cs":1},{"i":44687,"l":"6981.b1","iso":"6981.b","N":6981,"r":0,"t":"Z/2Z","to":2,"cm":0,"az":4.2546728,"al":0.316563,"lp":179,"ci":0,"cs":2},{"i":44688,"l":"6981.b2","iso":"6981.b","N":6981,"r":0,"t":"Z/2Z","to":2,"cm":0,"az":4.2510692,"al":0.3125128,"lp":179,"ci":1,"cs":2},{"i":39460,"l":"6258.r1","iso":"6258.r","N":6258,"r":1,"t":"0","to":1,"cm":0,"az":4.2829065,"al":0.4017668,"lp":149,"ci":0,"cs":1},{"i":43009,"l":"6740.a1","iso":"6740.a","N":6740,"r":1,"t":"Z/2Z","to":2,"cm":0,"az":4.209652,"al":0.342057,"lp":337,"ci":0,"cs":2},{"i":43010,"l":"6740.a2","iso":"6740.a","N":6740,"r":1,"t":"Z/2Z","to":2,"cm":0,"az":4.2059199,"al":0.3399987,"lp":337,"ci":1,"cs":2},{"i":43546,"l":"6821.b1","iso":"6821.b","N":6821,"r":1,"t":"0","to":1,"cm":0,"az":4.3620908,"al":0.3344058,"lp":359,"ci":0,"cs":1},{"i":42409,"l":"6672.a1","iso":"6672.a","N":6672,"r":1,"t":"0","to":1,"cm":0,"az":4.2021866,"al":0.3510457,"lp":139,"ci":0,"cs":2},{"i":42410,"l":"6672.a2","iso":"6672.a","N":6672,"r":1,"t":"0","to":1,"cm":0,"az":4.1944179,"al":0.3515508,"lp":139,"ci":1,"cs":2},{"i":39023,"l":"6192.w1","iso":"6192.w","N":6192,"r":0,"t":"0","to":1,"cm":0,"az":4.1903521,"al":0.4078542,"lp":43,"ci":0,"cs":1},{"i":44669,"l":"6976.d1","iso":"6976.d","N":6976,"r":1,"t":"0","to":1,"cm":0,"az":4.2551805,"al":0.3144025,"lp":109,"ci":0,"cs":1},{"i":42413,"l":"6672.d1","iso":"6672.d","N":6672,"r":0,"t":"Z/2Z","to":2,"cm":0,"az":4.2907053,"al":0.3509873,"lp":139,"ci":0,"cs":2},{"i":42414,"l":"6672.d2","iso":"6672.d","N":6672,"r":0,"t":"Z/2Z","to":2,"cm":0,"az":4.2866146,"al":0.3500695,"lp":139,"ci":1,"cs":2},{"i":41749,"l":"6562.a1","iso":"6562.a","N":6562,"r":0,"t":"0","to":1,"cm":0,"az":4.2023561,"al":0.3611393,"lp":193,"ci":0,"cs":1},{"i":39783,"l":"6310.a2","iso":"6310.a","N":6310,"r":1,"t":"0","to":1,"cm":0,"az":4.3367418,"al":0.3946435,"lp":631,"ci":0,"cs":2},{"i":43457,"l":"6807.f3","iso":"6807.f","N":6807,"r":1,"t":"Z/3Z","to":3,"cm":0,"az":4.2096322,"al":0.3332911,"lp":2269,"ci":2,"cs":3},{"i":39233,"l":"6224.c1","iso":"6224.c","N":6224,"r":1,"t":"0","to":1,"cm":0,"az":4.2817903,"al":0.4039538,"lp":389,"ci":0,"cs":1},{"i":38979,"l":"6190.c1","iso":"6190.c","N":6190,"r":1,"t":"0","to":1,"cm":0,"az":4.2836958,"al":0.4090733,"lp":619,"ci":0,"cs":1},{"i":39758,"l":"6306.a1","iso":"6306.a","N":6306,"r":0,"t":"Z/4Z","to":4,"cm":0,"az":4.2246948,"al":0.3930964,"lp":1051,"ci":2,"cs":4},{"i":39759,"l":"6306.a2","iso":"6306.a","N":6306,"r":0,"t":"Z/2Z \u00d7 Z/2Z","to":4,"cm":0,"az":4.2266517,"al":0.3957855,"lp":1051,"ci":3,"cs":4},{"i":42450,"l":"6677.b1","iso":"6677.b","N":6677,"r":0,"t":"0","to":1,"cm":0,"az":4.3524776,"al":0.3497424,"lp":607,"ci":0,"cs":1},{"i":39915,"l":"6334.b1","iso":"6334.b","N":6334,"r":2,"t":"0","to":1,"cm":0,"az":4.2364701,"al":0.3928537,"lp":3167,"ci":0,"cs":1},{"i":43237,"l":"6782.b1","iso":"6782.b","N":6782,"r":2,"t":"0","to":1,"cm":0,"az":4.2791146,"al":0.3395035,"lp":3391,"ci":0,"cs":1},{"i":40713,"l":"6418.a1","iso":"6418.a","N":6418,"r":1,"t":"Z/2Z","to":2,"cm":0,"az":4.2145215,"al":0.3817201,"lp":3209,"ci":0,"cs":2},{"i":40714,"l":"6418.a2","iso":"6418.a","N":6418,"r":1,"t":"Z/2Z","to":2,"cm":0,"az":4.2094268,"al":0.3781199,"lp":3209,"ci":1,"cs":2},{"i":39760,"l":"6306.a3","iso":"6306.a","N":6306,"r":0,"t":"Z/2Z","to":2,"cm":0,"az":4.2265625,"al":0.3967714,"lp":1051,"ci":0,"cs":4},{"i":39761,"l":"6306.a4","iso":"6306.a","N":6306,"r":0,"t":"Z/2Z","to":2,"cm":0,"az":4.2218828,"al":0.3982208,"lp":1051,"ci":1,"cs":4},{"i":43204,"l":"6774.g1","iso":"6774.g","N":6774,"r":1,"t":"0","to":1,"cm":0,"az":4.2365706,"al":0.3378697,"lp":1129,"ci":0,"cs":1},{"i":42533,"l":"6691.a1","iso":"6691.a","N":6691,"r":2,"t":"0","to":1,"cm":0,"az":4.2912111,"al":0.3484462,"lp":6691,"ci":0,"cs":1},{"i":41710,"l":"6558.d1","iso":"6558.d","N":6558,"r":0,"t":"0","to":1,"cm":0,"az":4.2754886,"al":0.3622135,"lp":1093,"ci":0,"cs":1},{"i":39063,"l":"6199.b1","iso":"6199.b","N":6199,"r":1,"t":"0","to":1,"cm":0,"az":4.3384394,"al":0.4064422,"lp":6199,"ci":0,"cs":1}]}